LICENSE
README.md
main.py
setup.py
contrib/arp.py
contrib/bernoulli_gates.py
contrib/bezier.py
contrib/binary_counter.py
contrib/bit_garden.py
contrib/bouncing_pixels.py
contrib/clock_mod.py
contrib/coin_toss.py
contrib/consequencer.py
contrib/conway.py
contrib/custom_font_demo.py
contrib/cvecorder.py
contrib/daily_random.py
contrib/dfam.py
contrib/dscn2.py
contrib/egressus_melodiam.py
contrib/envelope_generator.py
contrib/euclid.py
contrib/gate_phaser.py
contrib/gates_and_triggers.py
contrib/hamlet.py
contrib/harmonic_lfos.py
contrib/hello_world.py
contrib/http_control.py
contrib/itty_bitty.py
contrib/knob_playground.py
contrib/kompari.py
contrib/logic.py
contrib/lutra.py
contrib/master_clock.py
contrib/menu.py
contrib/morse.py
contrib/noddy_holder.py
contrib/ocean_surge.py
contrib/osc_control.py
contrib/pams.py
contrib/particle_physics.py
contrib/pet_rock.py
contrib/piconacci.py
contrib/poly_square.py
contrib/polyrhythmic_sequencer.py
contrib/probapoly.py
contrib/quantizer.py
contrib/radio_scanner.py
contrib/scope.py
contrib/sequential_switch.py
contrib/settings_menu_example.py
contrib/sigma.py
contrib/slopes.py
contrib/smooth_random_voltages.py
contrib/strange_attractor.py
contrib/traffic.py
contrib/turing_machine.py
contrib/volts.py
firmware/version.py
micropython_europi_contrib.egg-info/PKG-INFO
micropython_europi_contrib.egg-info/SOURCES.txt
micropython_europi_contrib.egg-info/dependency_links.txt
micropython_europi_contrib.egg-info/namespace_packages.txt
micropython_europi_contrib.egg-info/top_level.txt